[
    {
        "id": "1770719222945",
        "titre": "Brouillon depuis un atelier",
        "titre_en": "",
        "annee": "2025",
        "description": "",
        "description_en": "",
        "exhume_par": "",
        "categories": [],
        "categories_en": [],
        "url_qr": "",
        "location": "",
        "location_en": "",
        "coords": null,
        "image_path": "",
        "date": "2026-02-10",
        "created_at": "2026-02-10T10:27:02.945Z",
        "origin": "H2O",
        "visible": false,
        "status": "public_draft"
    },
    {
        "id": "1770720744098",
        "titre": "Brouillon depuis le g\u00e9n\u00e9rale 1",
        "titre_en": "",
        "annee": "2025",
        "description": "",
        "description_en": "",
        "exhume_par": "",
        "categories": [],
        "categories_en": [],
        "url_qr": "",
        "location": "",
        "location_en": "",
        "coords": null,
        "image_path": "",
        "date": "2026-02-10",
        "created_at": "2026-02-10T10:52:24.098Z",
        "status": "public_draft"
    },
    {
        "id": "1770720762694",
        "titre": "Deuxieme brouillon atelier",
        "titre_en": "",
        "annee": "2025",
        "description": "",
        "description_en": "",
        "exhume_par": "",
        "categories": [],
        "categories_en": [],
        "url_qr": "",
        "location": "",
        "location_en": "",
        "coords": null,
        "image_path": "",
        "date": "2026-02-10",
        "created_at": "2026-02-10T10:52:42.694Z",
        "status": "public_draft"
    },
    {
        "id": "1770720820870",
        "titre": "test brouillon",
        "titre_en": "",
        "annee": "2025",
        "description": "",
        "description_en": "",
        "exhume_par": "",
        "categories": [],
        "categories_en": [],
        "url_qr": "",
        "location": "",
        "location_en": "",
        "coords": null,
        "image_path": "",
        "date": "2026-02-10",
        "created_at": "2026-02-10T10:53:40.870Z",
        "status": "public_draft"
    },
    {
        "id": "1770720854050",
        "titre": "tests 333",
        "titre_en": "",
        "annee": "2025",
        "description": "",
        "description_en": "",
        "exhume_par": "",
        "categories": [],
        "categories_en": [],
        "url_qr": "",
        "location": "",
        "location_en": "",
        "coords": null,
        "image_path": "",
        "date": "2026-02-10",
        "created_at": "2026-02-10T10:54:14.050Z",
        "origin": "test",
        "workshopId": "1770720803006",
        "visible": false,
        "status": "public_draft"
    }
]